riverpy/__init__.py
riverpy/riverviewclient.py
riverpy/version.py
riverpy-0.1.2.dist-info/DESCRIPTION.rst
riverpy-0.1.2.dist-info/METADATA
riverpy-0.1.2.dist-info/metadata.json
riverpy-0.1.2.dist-info/RECORD
riverpy-0.1.2.dist-info/top_level.txt
riverpy-0.1.2.dist-info/WHEEL
