Metadata-Version: 2.0
Name: riverpy
Version: 0.1.2
Summary: Python client for River View
Home-page: http://github.com/nupic-community/riverpy
Author: Matthew Taylor
Author-email: matt@numenta.org
License: MIT
Keywords: river,view,client
Platform: UNKNOWN
Classifier: Development Status :: 5 - Production/Stable
Classifier: Environment :: Console
Classifier: Intended Audience :: Developers
Classifier: License :: OSI Approved :: MIT License
Classifier: Natural Language :: English
Classifier: Operating System :: OS Independent
Classifier: Programming Language :: Python
Requires-Dist: pytest (==2.4.2)
Requires-Dist: pytest-cov (==1.6)
Requires-Dist: mock (==1.0.1)
Requires-Dist: coverage (==3.7.1)
Requires-Dist: unittest2 (==0.5.1)
Requires-Dist: httpretty (==0.8.8)
Requires-Dist: sure (==1.2.10)
Requires-Dist: requests (==1.2.3)
Requires-Dist: simplejson (==3.6.5)
